lettucedetect/__init__.py
lettucedetect/ragfactchecker.py
lettucedetect/datasets/__init__.py
lettucedetect/datasets/hallucination_dataset.py
lettucedetect/detectors/__init__.py
lettucedetect/detectors/base.py
lettucedetect/detectors/cache.py
lettucedetect/detectors/factory.py
lettucedetect/detectors/llm.py
lettucedetect/detectors/prompt_utils.py
lettucedetect/detectors/rag_fact_checker.py
lettucedetect/detectors/transformer.py
lettucedetect/integrations/__init__.py
lettucedetect/integrations/elysia/README.md
lettucedetect/integrations/elysia/__init__.py
lettucedetect/integrations/elysia/example.py
lettucedetect/integrations/elysia/tools.py
lettucedetect/integrations/langchain/README.md
lettucedetect/integrations/langchain/__init__.py
lettucedetect/integrations/langchain/callbacks.py
lettucedetect/integrations/langchain/requirements.txt
lettucedetect/integrations/langchain/examples/rag_example.py
lettucedetect/integrations/langchain/examples/streamlit_app.py
lettucedetect/models/__init__.py
lettucedetect/models/evaluator.py
lettucedetect/models/generation.py
lettucedetect/models/inference.py
lettucedetect/models/trainer.py
lettucedetect/preprocess/__init__.py
lettucedetect/preprocess/preprocess_ragbench.py
lettucedetect/preprocess/preprocess_ragtruth.py
lettucedetect/prompts/examples_cn.json
lettucedetect/prompts/examples_de.json
lettucedetect/prompts/examples_en.json
lettucedetect/prompts/examples_es.json
lettucedetect/prompts/examples_fr.json
lettucedetect/prompts/examples_it.json
lettucedetect/prompts/examples_pl.json
lettucedetect/prompts/hallucination_detection.txt
lettucedetect/prompts/qa_prompt_cn.txt
lettucedetect/prompts/qa_prompt_de.txt
lettucedetect/prompts/qa_prompt_en.txt
lettucedetect/prompts/qa_prompt_es.txt
lettucedetect/prompts/qa_prompt_fr.txt
lettucedetect/prompts/qa_prompt_it.txt
lettucedetect/prompts/qa_prompt_pl.txt
lettucedetect/prompts/summary_prompt_cn.txt
lettucedetect/prompts/summary_prompt_de.txt
lettucedetect-0.1.8.dist-info/licenses/LICENSE
lettucedetect-0.1.8.dist-info/METADATA
lettucedetect-0.1.8.dist-info/WHEEL
lettucedetect-0.1.8.dist-info/top_level.txt
lettucedetect-0.1.8.dist-info/RECORD
