Metadata-Version: 2.4
Name: lettucedetect
Version: 0.1.8
Summary: Lettucedetect is a framework for detecting hallucinations in RAG applications.
Author-email: Adam Kovacs <kovacs@krlabs.eu>
License: MIT
Project-URL: Homepage, https://github.com/krlabsorg/lettucedetect
Classifier: Programming Language :: Python :: 3
Classifier: License :: OSI Approved :: MIT License
Classifier: Operating System :: OS Independent
Requires-Python: >=3.10
License-File: LICENSE
Requires-Dist: torch>=2.6.0
Requires-Dist: transformers>=4.48.3
Requires-Dist: tqdm>=4.65.0
Requires-Dist: scikit-learn>=1.6.1
Requires-Dist: numpy>=2.2.2
Requires-Dist: openai>=1.66.3
Requires-Dist: rag-fact-checker
Provides-Extra: dev
Requires-Dist: pytest>=7.0.0; extra == "dev"
Requires-Dist: pytest-cov>=4.0.0; extra == "dev"
Requires-Dist: pytest-asyncio>=0.25; extra == "dev"
Requires-Dist: ruff>=0.0.270; extra == "dev"
Provides-Extra: api
Requires-Dist: fastapi[standard]>=0.115; extra == "api"
Requires-Dist: pydantic-settings>=2.8.0; extra == "api"
Requires-Dist: httpx>=0.28; extra == "api"
Dynamic: license-file
